pikobs/__init__.py
pikobs/cardio/__init__.py
pikobs/cardio/cardio.py
pikobs/cardio/cardio_plot.py
pikobs/configobs/__init__.py
pikobs/configobs/delete_folder.py
pikobs/configobs/familyobs.py
pikobs/configobs/flags_criteria.py
pikobs/configobs/regionsobs.py
pikobs/configobs/type_boxes.py
pikobs/configobs/type_projection.py
pikobs/configobs/type_varno.py
pikobs/extension/libudfsqlite-shared.so
pikobs/flags/__init__.py
pikobs/flags/flags.py
pikobs/flags/flags_count.py
pikobs/flags/flags_plot.py
pikobs/flags/flags_plot0.py
pikobs/flags/flags_plot3.py
pikobs/flags/flags_plotv2.py
pikobs/flags/plotpo.py
pikobs/flags/plotpo2.py
pikobs/flags/plotpo3.py
pikobs/flags/plotpo4.py
pikobs/flags/plotpo5.py
pikobs/histogram/__init__.py
pikobs/histogram/histogram.py
pikobs/histogram/histogram_plot.py
pikobs/profile/__init__.py
pikobs/profile/profile.py
pikobs/profile/profile_plot.py
pikobs/scatter/__init__.py
pikobs/scatter/scatter.py
pikobs/scatter/scatter_plot.py
pikobs/timeserie/__init__.py
pikobs/timeserie/timeserie.py
pikobs/timeserie/timeserie_plot.py
pikobs/unittest/__init__.py
pikobs/unittest/unittest.py
pikobs/unittest/unittest_timeserie.py
pikobs/vdedr/__init__.py
pikobs/vdedr/vdedr.py
pikobs/vdedr/vdedr_plot.py
pikobs/zone/__init__.py
pikobs/zone/zone.py
pikobs/zone/zone_plot.py
pikobs-2.0.58.dist-info/METADATA
pikobs-2.0.58.dist-info/WHEEL
pikobs-2.0.58.dist-info/top_level.txt
pikobs-2.0.58.dist-info/RECORD
